README.md
setup.py
openvpn3_handler/__init__.py
openvpn3_handler/constants.py
openvpn3_handler/io.py
openvpn3_handler/main.py
openvpn3_handler.egg-info/PKG-INFO
openvpn3_handler.egg-info/SOURCES.txt
openvpn3_handler.egg-info/dependency_links.txt
openvpn3_handler.egg-info/entry_points.txt
openvpn3_handler.egg-info/requires.txt
openvpn3_handler.egg-info/top_level.txt